BioFusion/__init__.py
BioFusion/_modidx.py
BioFusion/cmmd.py
BioFusion/download_data.py
BioFusion/utils.py
BioFusion/bin/molti
BioFusion/bin/molti-dream
biofusion-0.0.6.dist-info/LICENSE
biofusion-0.0.6.dist-info/METADATA
biofusion-0.0.6.dist-info/WHEEL
biofusion-0.0.6.dist-info/entry_points.txt
biofusion-0.0.6.dist-info/top_level.txt
biofusion-0.0.6.dist-info/RECORD
