Metadata-Version: 2.2
Name: biofusion
Version: 0.0.6
Summary: Multilayer networks for biological multimodal data fusion and analysis.
Home-page: https://github.com/CalmScout/BioFusion
Author: Anton Popov
Author-email: anton.popov@bsc.es
License: MIT License
Keywords: multimodal network biolobical
Classifier: Development Status :: 4 - Beta
Classifier: Intended Audience :: Developers
Classifier: Natural Language :: English
Classifier: Programming Language :: Python :: 3.7
Classifier: Programming Language :: Python :: 3.8
Classifier: Programming Language :: Python :: 3.9
Classifier: Programming Language :: Python :: 3.10
Classifier: Programming Language :: Python :: 3.11
Classifier: Programming Language :: Python :: 3.12
Classifier: License :: OSI Approved :: MIT License
Requires-Python: >=3.7
License-File: LICENSE
Requires-Dist: numpy
Requires-Dist: scipy
Requires-Dist: seaborn
Requires-Dist: tqdm
Requires-Dist: rdflib
Requires-Dist: joblib
Requires-Dist: cobra
Requires-Dist: networkx
Requires-Dist: pympler
Requires-Dist: memory-profiler
Requires-Dist: ipywidgets
Requires-Dist: nbdev
Requires-Dist: jupyterlab
Requires-Dist: jupyterlab-quarto
Requires-Dist: ray[data,serve,train,tune]
Requires-Dist: bioc
Provides-Extra: dev
Dynamic: author
Dynamic: author-email
Dynamic: classifier
Dynamic: description
Dynamic: description-content-type
Dynamic: home-page
Dynamic: keywords
Dynamic: license
Dynamic: provides-extra
Dynamic: requires-dist
Dynamic: requires-python
Dynamic: summary
